{"/":{"title":"Hacking Attention","content":"\n[[x]]\n\n[[y]]\n\n[[z]]\n","lastmodified":"2022-10-12T15:29:31.995320326Z","tags":null},"/a":{"title":"a","content":"\n[[b]]","lastmodified":"2022-10-12T15:29:31.995320326Z","tags":null},"/b":{"title":"b","content":"[[c]]","lastmodified":"2022-10-12T15:29:31.995320326Z","tags":null},"/c":{"title":"c","content":"[[d]]","lastmodified":"2022-10-12T15:29:31.995320326Z","tags":null},"/d":{"title":"d","content":"[[a]]","lastmodified":"2022-10-12T15:29:31.995320326Z","tags":null},"/x":{"title":"x","content":"[x](x.md)\n\n[z](z.md)","lastmodified":"2022-10-12T15:29:31.995320326Z","tags":null},"/y":{"title":"y","content":"[z](z.md)","lastmodified":"2022-10-12T15:29:31.995320326Z","tags":null},"/z":{"title":"z","content":"[x](x.md)\n[y](y.md)","lastmodified":"2022-10-12T15:29:31.995320326Z","tags":null}}